{
	"moduleDescription"  :
	{
		"title"          : "Circular Statistics",
		"description"    : "This module offers basic methods for directional data.",
		"version"        : 1,
		"author"         : "Aaron Bahde",
		"maintainer"     : "JASP Team <info@jasp-stats.org>",
		"website"        : "jasp-stats.org",
		"license"        : "GPL (>= 2)",
		"dynamic"        : true
	},
	
	"ribbonEntries":
	[
		{
			"title":	"Descriptives",
			"icon":		"analysis-circstats-descriptives.svg",
			"analyses":
			[
				{
					"title":	"Descriptives",
					"qml": "CircularStatisticsDescriptives.qml",
					"function":	"CircularStatisticsDescriptives",
					"usesJaspResults": true
				}
			]
		},
		{
			"title":	"Hypothesis-Testing",
			"icon":		"analysis-circstats-descriptives.svg",
			"analyses":
			[
				{
					"title":	"One-Sample Tests",
					"qml": "CircularStatisticsOneSampleTests.qml",
					"function":	"CircularStatisticsOneSampleTests",
					"usesJaspResults": true
				},
				{
					"title":	"Multiple-Sample Tests",
					"qml": "CircularStatisticsMultipleSampleTests.qml",
					"function":	"CircularStatisticsMultipleSampleTests",
					"usesJaspResults": true
				}
			]
		}
	]
}
